aiassistant/__init__.py
aiassistant/aiassistant.py
aiassistant_raayan-0.1.0.dist-info/LICENSE
aiassistant_raayan-0.1.0.dist-info/METADATA
aiassistant_raayan-0.1.0.dist-info/WHEEL
aiassistant_raayan-0.1.0.dist-info/top_level.txt
aiassistant_raayan-0.1.0.dist-info/RECORD
