Metadata-Version: 2.2
Name: aiassistant-raayan
Version: 0.1.0
Summary: A Python module for AI functionalities like sentiment analysis, text summarization, and question answering using Hugging Face Transformers.
Author: Your Name
Author-email: your.email@example.com
Classifier: Programming Language :: Python :: 3
Classifier: License :: OSI Approved :: MIT License
Classifier: Operating System :: OS Independent
Requires-Python: >=3.6
License-File: LICENSE
Requires-Dist: transformers
Requires-Dist: torch
Dynamic: author
Dynamic: author-email
Dynamic: classifier
Dynamic: requires-dist
Dynamic: requires-python
Dynamic: summary
